

test1:
0   LOAD_CONST               97        
1   RETURN_VALUE             0         
2   RETURN_NONE              

test2:
SymbolEntry(a1, Variable, Local, Location(5, 11))
0   LOAD_CONST               97        
1   RETURN_VALUE             0         
2   RETURN_NONE              

main:
0   CALL_FUNCTION            0         test1               
1   PRINT_CHARACTER          0         
2   PRINT_NEWLINE            0         
3   LOAD_CONST               1         
4   CALL_FUNCTION            1         test2               
5   PRINT_CHARACTER          0         
6   PRINT_NEWLINE            0         
7   RETURN_NONE              


